trainline/__init__.py
trainline/stations_mini.csv
trainline-0.1.2.data/scripts/trainline_cli.py
trainline-0.1.2.dist-info/LICENSE
trainline-0.1.2.dist-info/METADATA
trainline-0.1.2.dist-info/WHEEL
trainline-0.1.2.dist-info/top_level.txt
trainline-0.1.2.dist-info/RECORD
