Metadata-Version: 2.1
Name: trainline
Version: 0.1.2
Summary: Non-official Python wrapper and CLI tool for Trainline
Home-page: https://github.com/tducret/trainline-python
Author: Thibault Ducret
Author-email: hello@tducret.com
License: MIT license
Download-URL: https://github.com/tducret/trainline-python/tarball/0.1.2
Keywords: api,trainline,parsing,train,sncf,python-wrapper,scraping,scraper,parser
Platform: Posix; MacOS X
Classifier: License :: OSI Approved :: MIT License
Classifier: Programming Language :: Python :: 3
Requires-Python: >=3
Requires-Dist: click (>=6.7)
Requires-Dist: pytz (>=2018.5)
